cla_6bit.v
module cla6_bit(
    input [5:0] A, B,
    input c0,
    output [5:0] S,
    output c_out
    );

    wire c1, c2, c3, c4, c5, c6;
    wire p0, p1, p2, p3, p4, p5;
    wire g0, g1, g2, g3, g4, g5;

    and And0(g0, A[0], B[0]);
    and And1(g1, A[1], B[1]);
    and And2(g2, A[2], B[2]);
    and And3(g3, A[3], B[3]);
    and And4(g4, A[4], B[4]);
    and And5(g5, A[5], B[5]);

    or Or0(p0, A[0], B[0]);
    or Or1(p1, A[1], B[1]);
    or Or2(p2, A[2], B[2]);
    or Or3(p3, A[3], B[3]);
    or Or4(p4, A[4], B[4]);
    or Or5(p5, A[5], B[5]);

    wire c1a1;
    and c1and1(c1a1, p0, c0);
    or  c1or1(c1, c1a1, g0);
    xor s0xor1(S[0], A[0], B[0], c0);

    wire c2a2, c2a1;
    and c2and1(c2a1, p1, g0);
    and c2and2(c2a2, p1, p0, c0);
    or  c2or1(c2, c2a2, c2a1, g1);
    xor s1xor1(S[1], A[1], B[1], c1);

    wire c3a3, c3a2, c3a1;
    and c3and1(c3a1, p2, g1);
    and c3and2(c3a2, p2, p1, g0);
    and c3and3(c3a3, p2, p1, p0, c0);
    or  c3or1(c3, c3a3, c3a2, c3a1, g2);
    xor s2xor1(S[2], A[2], B[2], c2);

    wire c4a4, c4a3, c4a2, c4a1;
    and c4and1(c4a1, p3, g2);
    and c4and2(c4a2, p3, p2, g1);
    and c4and3(c4a3, p3, p2, p1, g0);
    and c4and4(c4a4, p3, p2, p1, p0, c0);
    or  c4or1(c4, c4a4, c4a3, c4a2, c4a1, g3);
    xor s3xor1(S[3], A[3], B[3], c3);

    wire c5a5, c5a4, c5a3, c5a2, c5a1;
    and c5and1(c5a1, p4, g3);
    and c5and2(c5a2, p4, p3, g2);
    and c5and3(c5a3, p4, p3, p2, g1);
    and c5and4(c5a4, p4, p3, p2, p1, g0);
    and c5and5(c5a5, p4, p3, p2, p1, p0, c0);
    or  c5or1(c5, c5a5, c5a4, c5a3, c5a2, c5a1, g4);
    xor s4xor1(S[4], A[4], B[4], c4);

    wire c6a6, c6a5, c6a4, c6a3, c6a2, c6a1;
    and c6and1(c6a1, p5, g4);
    and c6and2(c6a2, p5, p4, g3);
    and c6and3(c6a3, p5, p4, p3, g2);
    and c6and4(c6a4, p5, p4, p3, p2, g1);
    and c6and5(c6a5, p5, p4, p3, p2, p1, g0);
    and c6and6(c6a6, p5, p4, p3, p2, p1, p0, c0);
    or  c6or1(c6, c6a6, c6a5, c6a4, c6a3, c6a2, c6a1, g5);
    xor s5xor1(S[5], A[5], B[5], c5);

    assign c_out = c6;

endmodule

cla_6bit_tb.v
`timescale 1ns / 100ps
module cla_6bit_tb;
    wire [5:0] A, B;
    wire c0;
    wire [5:0] S;
    wire c_out;

    cla6_bit adder(A, B, c0, S, c_out);
    integer i;
    assign c0 = 1'b0;
    assign {A, B} = i[11:0];
    wire [6:0] total;
    assign total = {c_out, S};

    initial begin
        for(i = 0; i < 4096; i = i+1) begin
            #20
            $display("A:%d, B:%d, => S:%d, Cout:%b, Total:%d", A, B, S, c_out, total);
            if(A+B != S) begin
                $display("Error: %d + %d != %d", A, B, S);
                $stop;
            end
        end
    end

    initial begin
        $dumpfile("cla_6bit_tb.vcd");
        $dumpvars(0, cla_6bit_tb);
    end
endmodule

OutputFiles/cla_6bit_tb.vcd
$date
	Tue Oct 01 12:45:18 2024
$end
$version
	Icarus Verilog
$end
$timescale
	100ps
$end
$scope module cla_6bit_tb $end
$var wire 1 ! c0 $end
$var wire 7 " total [6:0] $end
$var wire 1 # c_out $end
$var wire 6 $ S [5:0] $end
$var wire 6 % B [5:0] $end
$var wire 6 & A [5:0] $end
$var integer 32 ' i [31:0] $end
$scope module adder $end
$var wire 6 ( A [5:0] $end
$var wire 6 ) B [5:0] $end
$var wire 1 ! c0 $end
$var wire 1 * c1 $end
$var wire 1 + c1a1 $end
$var wire 1 , c2 $end
$var wire 1 - c2a1 $end
$var wire 1 . c2a2 $end
$var wire 1 / c3 $end
$var wire 1 0 c3a1 $end
$var wire 1 1 c3a2 $end
$var wire 1 2 c3a3 $end
$var wire 1 3 c4 $end
$var wire 1 4 c4a1 $end
$var wire 1 5 c4a2 $end
$var wire 1 6 c4a3 $end
$var wire 1 7 c4a4 $end
$var wire 1 8 c5 $end
$var wire 1 9 c5a1 $end
$var wire 1 : c5a2 $end
$var wire 1 ; c5a3 $end
$var wire 1 < c5a4 $end
$var wire 1 = c5a5 $end
$var wire 1 > c6 $end
$var wire 1 ? c6a1 $end
$var wire 1 @ c6a2 $end
$var wire 1 A c6a3 $end
$var wire 1 B c6a4 $end
$var wire 1 C c6a5 $end
$var wire 1 D c6a6 $end
$var wire 1 # c_out $end
$var wire 1 E g0 $end
$var wire 1 F g1 $end
$var wire 1 G g2 $end
$var wire 1 H g3 $end
$var wire 1 I g4 $end
$var wire 1 J g5 $end
$var wire 1 K p0 $end
$var wire 1 L p1 $end
$var wire 1 M p2 $end
$var wire 1 N p3 $end
$var wire 1 O p4 $end
$var wire 1 P p5 $end
$var wire 6 Q S [5:0] $end
$upscope $end
$upscope $end
$enddefinitions $end
$comment Show the parameter values. $end
$dumpall
$end
#0
$dumpvars
b0 Q
0P
0O
0N
0M
0L
0K
0J
0I
0H
0G
0F
0E
0D
0C
0B
0A
0@
0?
0>
0=
0<
0;
0:
09
08
07
06
05
04
03
02
01
00
0/
0.
0-
0,
0+
0*
b0 )
b0 (
b0 '
b0 &
b0 %
b0 $
0#
b0 "
0!
$end
#200
1K
b1 "
b1 $
b1 Q
b1 %
b1 )
b1 '
#400
0K
1L
b10 "
b10 $
b10 Q
b10 %
b10 )
b10 '
#600
1K
b11 "
b11 $
b11 Q
b11 %
b11 )
b11 '
#800
0K
0L
1M
b100 "
b100 $
b100 Q
b100 %
b100 )
b100 '
#1000
1K
b101 "
b101 $
b101 Q
b101 %
b101 )
b101 '
#1200
0K
1L
b110 "
b110 $
b110 Q
b110 %
b110 )
b110 '
#1400
1K
b111 "
b111 $
b111 Q
b111 %
b111 )
b111 '
#1600
0K
0L
0M
1N
b1000 "
b1000 $
b1000 Q
b1000 %
b1000 )
b1000 '
#1800
1K
b1001 "
b1001 $
b1001 Q
b1001 %
b1001 )
b1001 '
#2000
0K
1L
b1010 "
b1010 $
b1010 Q
b1010 %
b1010 )
b1010 '
#2200
1K
b1011 "
b1011 $
b1011 Q
b1011 %
b1011 )
b1011 '
#2400
0K
0L
1M
b1100 "
b1100 $
b1100 Q
b1100 %
b1100 )
b1100 '
#2600
1K
b1101 "
b1101 $
b1101 Q
b1101 %
b1101 )
b1101 '
#2800
0K
1L
b1110 "
b1110 $
b1110 Q
b1110 %
b1110 )
b1110 '
#3000
1K
b1111 "
b1111 $
b1111 Q
b1111 %
b1111 )
b1111 '
#3200
0K
0L
0M
0N
1O
b10000 "
b10000 $
b10000 Q
b10000 %
b10000 )
b10000 '
#3400
1K
b10001 "
b10001 $
b10001 Q
b10001 %
b10001 )
b10001 '
#3600
0K
1L
b10010 "
b10010 $
b10010 Q
b10010 %
b10010 )
b10010 '
#3800
1K
b10011 "
b10011 $
b10011 Q
b10011 %
b10011 )
b10011 '
#4000
0K
0L
1M
b10100 "
b10100 $
b10100 Q
b10100 %
b10100 )
b10100 '
#4200
1K
b10101 "
b10101 $
b10101 Q
b10101 %
b10101 )
b10101 '
#4400
0K
1L
b10110 "
b10110 $
b10110 Q
b10110 %
b10110 )
b10110 '
#4600
1K
b10111 "
b10111 $
b10111 Q
b10111 %
b10111 )
b10111 '
#4800
0K
0L
0M
1N
b11000 "
b11000 $
b11000 Q
b11000 %
b11000 )
b11000 '
#5000
1K
b11001 "
b11001 $
b11001 Q
b11001 %
b11001 )
b11001 '
#5200
0K
1L
b11010 "
b11010 $
b11010 Q
b11010 %
b11010 )
b11010 '
#5400
1K
b11011 "
b11011 $
b11011 Q
b11011 %
b11011 )
b11011 '
#5600
0K
0L
1M
b11100 "
b11100 $
b11100 Q
b11100 %
b11100 )
b11100 '
#5800
1K
b11101 "
b11101 $
b11101 Q
b11101 %
b11101 )
b11101 '
#6000
0K
1L
b11110 "
b11110 $
b11110 Q
b11110 %
b11110 )
b11110 '
#6200
1K
b11111 "
b11111 $
b11111 Q
b11111 %
b11111 )
b11111 '
#6400
0K
0L
0M
0N
0O
1P
b100000 "
b100000 $
b100000 Q
b100000 %
b100000 )
b100000 '
#6600
1K
b100001 "
b100001 $
b100001 Q
b100001 %
b100001 )
b100001 '
#6800
0K
1L
b100010 "
b100010 $
b100010 Q
b100010 %
b100010 )
b100010 '
#7000
1K
b100011 "
b100011 $
b100011 Q
b100011 %
b100011 )
b100011 '
#7200
0K
0L
1M
b100100 "
b100100 $
b100100 Q
b100100 %
b100100 )
b100100 '
#7400
1K
b100101 "
b100101 $
b100101 Q
b100101 %
b100101 )
b100101 '
#7600
0K
1L
b100110 "
b100110 $
b100110 Q
b100110 %
b100110 )
b100110 '
#7800
1K
b100111 "
b100111 $
b100111 Q
b100111 %
b100111 )
b100111 '
#8000
0K
0L
0M
1N
b101000 "
b101000 $
b101000 Q
b101000 %
b101000 )
b101000 '
#8200
1K
b101001 "
b101001 $
b101001 Q
b101001 %
b101001 )
b101001 '
#8400
0K
1L
b101010 "
b101010 $
b101010 Q
b101010 %
b101010 )
b101010 '
#8600
1K
b101011 "
b101011 $
b101011 Q
b101011 %
b101011 )
b101011 '
#8800
0K
0L
1M
b101100 "
b101100 $
b101100 Q
b101100 %
b101100 )
b101100 '
#9000
1K
b101101 "
b101101 $
b101101 Q
b101101 %
b101101 )
b101101 '
#9200
0K
1L
b101110 "
b101110 $
b101110 Q
b101110 %
b101110 )
b101110 '
#9400
1K
b101111 "
b101111 $
b101111 Q
b101111 %
b101111 )
b101111 '
#9600
0K
0L
0M
0N
1O
b110000 "
b110000 $
b110000 Q
b110000 %
b110000 )
b110000 '
#9800
1K
b110001 "
b110001 $
b110001 Q
b110001 %
b110001 )
b110001 '
#10000
0K
1L
b110010 "
b110010 $
b110010 Q
b110010 %
b110010 )
b110010 '
#10200
1K
b110011 "
b110011 $
b110011 Q
b110011 %
b110011 )
b110011 '
#10400
0K
0L
1M
b110100 "
b110100 $
b110100 Q
b110100 %
b110100 )
b110100 '
#10600
1K
b110101 "
b110101 $
b110101 Q
b110101 %
b110101 )
b110101 '
#10800
0K
1L
b110110 "
b110110 $
b110110 Q
b110110 %
b110110 )
b110110 '
#11000
1K
b110111 "
b110111 $
b110111 Q
b110111 %
b110111 )
b110111 '
#11200
0K
0L
0M
1N
b111000 "
b111000 $
b111000 Q
b111000 %
b111000 )
b111000 '
#11400
1K
b111001 "
b111001 $
b111001 Q
b111001 %
b111001 )
b111001 '
#11600
0K
1L
b111010 "
b111010 $
b111010 Q
b111010 %
b111010 )
b111010 '
#11800
1K
b111011 "
b111011 $
b111011 Q
b111011 %
b111011 )
b111011 '
#12000
0K
0L
1M
b111100 "
b111100 $
b111100 Q
b111100 %
b111100 )
b111100 '
#12200
1K
b111101 "
b111101 $
b111101 Q
b111101 %
b111101 )
b111101 '
#12400
0K
1L
b111110 "
b111110 $
b111110 Q
b111110 %
b111110 )
b111110 '
#12600
1K
b111111 "
b111111 $
b111111 Q
b111111 %
b111111 )
b111111 '
#12800
0L
0M
0N
0O
0P
b1 "
b1 $
b1 Q
b0 %
b0 )
b1 &
b1 (
b1000000 '
#13000
1*
1E
b10 "
b10 $
b10 Q
b1 %
b1 )
b1000001 '
#13200
0*
0E
1L
b11 "
b11 $
b11 Q
b10 %
b10 )
b1000010 '
#13400
1,
1*
1-
1E
b100 "
b100 $
b100 Q
b11 %
b11 )
b1000011 '
#13600
0,
0*
0-
0E
0L
1M
b101 "
b101 $
b101 Q
b100 %
b100 )
b1000100 '
#13800
1*
1E
b110 "
b110 $
b110 Q
b101 %
b101 )
b1000101 '
#14000
0*
0E
1L
b111 "
b111 $
b111 Q
b110 %
b110 )
b1000110 '
#14200
1,
1/
1*
1-
11
1E
b1000 "
b1000 $
b1000 Q
b111 %
b111 )
b1000111 '
#14400
0,
0/
0*
0-
01
0E
0L
0M
1N
b1001 "
b1001 $
b1001 Q
b1000 %
b1000 )
b1001000 '
#14600
1*
1E
b1010 "
b1010 $
b1010 Q
b1001 %
b1001 )
b1001001 '
#14800
0*
0E
1L
b1011 "
b1011 $
b1011 Q
b1010 %
b1010 )
b1001010 '
#15000
1,
1*
1-
1E
b1100 "
b1100 $
b1100 Q
b1011 %
b1011 )
b1001011 '
#15200
0,
0*
0-
0E
0L
1M
b1101 "
b1101 $
b1101 Q
b1100 %
b1100 )
b1001100 '
#15400
1*
1E
b1110 "
b1110 $
b1110 Q
b1101 %
b1101 )
b1001101 '
#15600
0*
0E
1L
b1111 "
b1111 $
b1111 Q
b1110 %
b1110 )
b1001110 '
#15800
13
1,
1/
1*
1-
11
16
1E
b10000 "
b10000 $
b10000 Q
b1111 %
b1111 )
b1001111 '
#16000
03
0,
0/
0*
0-
01
06
0E
0L
0M
0N
1O
b10001 "
b10001 $
b10001 Q
b10000 %
b10000 )
b1010000 '
#16200
1*
1E
b10010 "
b10010 $
b10010 Q
b10001 %
b10001 )
b1010001 '
#16400
0*
0E
1L
b10011 "
b10011 $
b10011 Q
b10010 %
b10010 )
b1010010 '
#16600
1,
1*
1-
1E
b10100 "
b10100 $
b10100 Q
b10011 %
b10011 )
b1010011 '
#16800
0,
0*
0-
0E
0L
1M
b10101 "
b10101 $
b10101 Q
b10100 %
b10100 )
b1010100 '
#17000
1*
1E
b10110 "
b10110 $
b10110 Q
b10101 %
b10101 )
b1010101 '
#17200
0*
0E
1L
b10111 "
b10111 $
b10111 Q
b10110 %
b10110 )
b1010110 '
#17400
1,
1/
1*
1-
11
1E
b11000 "
b11000 $
b11000 Q
b10111 %
b10111 )
b1010111 '
#17600
0,
0/
0*
0-
01
0E
0L
0M
1N
b11001 "
b11001 $
b11001 Q
b11000 %
b11000 )
b1011000 '
#17800
1*
1E
b11010 "
b11010 $
b11010 Q
b11001 %
b11001 )
b1011001 '
#18000
0*
0E
1L
b11011 "
b11011 $
b11011 Q
b11010 %
b11010 )
b1011010 '
#18200
1,
1*
1-
1E
b11100 "
b11100 $
b11100 Q
b11011 %
b11011 )
b1011011 '
#18400
0,
0*
0-
0E
0L
1M
b11101 "
b11101 $
b11101 Q
b11100 %
b11100 )
b1011100 '
#18600
1*
1E
b11110 "
b11110 $
b11110 Q
b11101 %
b11101 )
b1011101 '
#18800
0*
0E
1L
b11111 "
b11111 $
b11111 Q
b11110 %
b11110 )
b1011110 '
#19000
18
13
1,
1/
1<
1*
1-
11
16
1E
b100000 "
b100000 $
b100000 Q
b11111 %
b11111 )
b1011111 '
#19200
08
03
0,
0/
0<
0*
0-
01
06
0E
0L
0M
0N
0O
1P
b100001 "
b100001 $
b100001 Q
b100000 %
b100000 )
b1100000 '
#19400
1*
1E
b100010 "
b100010 $
b100010 Q
b100001 %
b100001 )
b1100001 '
#19600
0*
0E
1L
b100011 "
b100011 $
b100011 Q
b100010 %
b100010 )
b1100010 '
#19800
1,
1*
1-
1E
b100100 "
b100100 $
b100100 Q
b100011 %
b100011 )
b1100011 '
#20000
0,
0*
0-
0E
0L
1M
b100101 "
b100101 $
b100101 Q
b100100 %
b100100 )
b1100100 '
#20200
1*
1E
b100110 "
b100110 $
b100110 Q
b100101 %
b100101 )
b1100101 '
#20400
0*
0E
1L
b100111 "
b100111 $
b100111 Q
b100110 %
b100110 )
b1100110 '
#20600
1,
1/
1*
1-
11
1E
b101000 "
b101000 $
b101000 Q
b100111 %
b100111 )
b1100111 '
#20800
0,
0/
0*
0-
01
0E
0L
0M
1N
b101001 "
b101001 $
b101001 Q
b101000 %
b101000 )
b1101000 '
#21000
1*
1E
b101010 "
b101010 $
b101010 Q
b101001 %
b101001 )
b1101001 '
#21200
0*
0E
1L
b101011 "
b101011 $
b101011 Q
b101010 %
b101010 )
b1101010 '
#21400
1,
1*
1-
1E
b101100 "
b101100 $
b101100 Q
b101011 %
b101011 )
b1101011 '
#21600
0,
0*
0-
0E
0L
1M
b101101 "
b101101 $
b101101 Q
b101100 %
b101100 )
b1101100 '
#21800
1*
1E
b101110 "
b101110 $
b101110 Q
b101101 %
b101101 )
b1101101 '
#22000
0*
0E
1L
b101111 "
b101111 $
b101111 Q
b101110 %
b101110 )
b1101110 '
#22200
13
1,
1/
1*
1-
11
16
1E
b110000 "
b110000 $
b110000 Q
b101111 %
b101111 )
b1101111 '
#22400
03
0,
0/
0*
0-
01
06
0E
0L
0M
0N
1O
b110001 "
b110001 $
b110001 Q
b110000 %
b110000 )
b1110000 '
#22600
1*
1E
b110010 "
b110010 $
b110010 Q
b110001 %
b110001 )
b1110001 '
#22800
0*
0E
1L
b110011 "
b110011 $
b110011 Q
b110010 %
b110010 )
b1110010 '
#23000
1,
1*
1-
1E
b110100 "
b110100 $
b110100 Q
b110011 %
b110011 )
b1110011 '
#23200
0,
0*
0-
0E
0L
1M
b110101 "
b110101 $
b110101 Q
b110100 %
b110100 )
b1110100 '
#23400
1*
1E
b110110 "
b110110 $
b110110 Q
b110101 %
b110101 )
b1110101 '
#23600
0*
0E
1L
b110111 "
b110111 $
b110111 Q
b110110 %
b110110 )
b1110110 '
#23800
1,
1/
1*
1-
11
1E
b111000 "
b111000 $
b111000 Q
b110111 %
b110111 )
b1110111 '
#24000
0,
0/
0*
0-
01
0E
0L
0M
1N
b111001 "
b111001 $
b111001 Q
b111000 %
b111000 )
b1111000 '
#24200
1*
1E
b111010 "
b111010 $
b111010 Q
b111001 %
b111001 )
b1111001 '
#24400
0*
0E
1L
b111011 "
b111011 $
b111011 Q
b111010 %
b111010 )
b1111010 '
#24600
1,
1*
1-
1E
b111100 "
b111100 $
b111100 Q
b111011 %
b111011 )
b1111011 '
#24800
0,
0*
0-
0E
0L
1M
b111101 "
b111101 $
b111101 Q
b111100 %
b111100 )
b1111100 '
#25000
1*
1E
b111110 "
b111110 $
b111110 Q
b111101 %
b111101 )
b1111101 '
#25200
0*
0E
1L
b111111 "
b111111 $
b111111 Q
b111110 %
b111110 )
b1111110 '
#25400
18
1#
1>
13
1,
1/
1<
1C
1*
1-
11
16
1E
b1000000 "
b0 $
b0 Q
b111111 %
b111111 )
b1111111 '
#25600
08
0#
0>
03
0,
0/
0<
0C
0*
0-
01
06
0M
0N
0O
0P
b10 "
b10 $
b10 Q
0E
0K
b0 %
b0 )
b10 &
b10 (
b10000000 '
#25800
1K
b11 "
b11 $
b11 Q
b1 %
b1 )
b10000001 '
#26000
1,
1F
0K
b100 "
b100 $
b100 Q
b10 %
b10 )
b10000010 '
#26200
1K
b101 "
b101 $
b101 Q
b11 %
b11 )
b10000011 '
#26400
0,
0F
0K
1M
b110 "
b110 $
b110 Q
b100 %
b100 )
b10000100 '
#26600
1K
b111 "
b111 $
b111 Q
b101 %
b101 )
b10000101 '
#26800
1/
1,
10
1F
0K
b1000 "
b1000 $
b1000 Q
b110 %
b110 )
b10000110 '
#27000
1K
b1001 "
b1001 $
b1001 Q
b111 %
b111 )
b10000111 '
#27200
0/
0,
00
0F
0K
0M
1N
b1010 "
b1010 $
b1010 Q
b1000 %
b1000 )
b10001000 '
#27400
1K
b1011 "
b1011 $
b1011 Q
b1001 %
b1001 )
b10001001 '
#27600
1,
1F
0K
b1100 "
b1100 $
b1100 Q
b1010 %
b1010 )
b10001010 '
#27800
1K
b1101 "
b1101 $
b1101 Q
b1011 %
b1011 )
b10001011 '
#28000
0,
0F
0K
1M
b1110 "
b1110 $
b1110 Q
b1100 %
b1100 )
b10001100 '
#28200
1K
b1111 "
b1111 $
b1111 Q
b1101 %
b1101 )
b10001101 '
#28400
13
1/
1,
10
15
1F
0K
b10000 "
b10000 $
b10000 Q
b1110 %
b1110 )
b10001110 '
#28600
1K
b10001 "
b10001 $
b10001 Q
b1111 %
b1111 )
b10001111 '
#28800
03
0/
0,
00
05
0F
0K
0M
0N
1O
b10010 "
b10010 $
b10010 Q
b10000 %
b10000 )
b10010000 '
#29000
1K
b10011 "
b10011 $
b10011 Q
b10001 %
b10001 )
b10010001 '
#29200
1,
1F
0K
b10100 "
b10100 $
b10100 Q
b10010 %
b10010 )
b10010010 '
#29400
1K
b10101 "
b10101 $
b10101 Q
b10011 %
b10011 )
b10010011 '
#29600
0,
0F
0K
1M
b10110 "
b10110 $
b10110 Q
b10100 %
b10100 )
b10010100 '
#29800
1K
b10111 "
b10111 $
b10111 Q
b10101 %
b10101 )
b10010101 '
#30000
1/
1,
10
1F
0K
b11000 "
b11000 $
b11000 Q
b10110 %
b10110 )
b10010110 '
#30200
1K
b11001 "
b11001 $
b11001 Q
b10111 %
b10111 )
b10010111 '
#30400
0/
0,
00
0F
0K
0M
1N
b11010 "
b11010 $
b11010 Q
b11000 %
b11000 )
b10011000 '
#30600
1K
b11011 "
b11011 $
b11011 Q
b11001 %
b11001 )
b10011001 '
#30800
1,
1F
0K
b11100 "
b11100 $
b11100 Q
b11010 %
b11010 )
b10011010 '
#31000
1K
b11101 "
b11101 $
b11101 Q
b11011 %
b11011 )
b10011011 '
#31200
0,
0F
0K
1M
b11110 "
b11110 $
b11110 Q
b11100 %
b11100 )
b10011100 '
#31400
1K
b11111 "
b11111 $
b11111 Q
b11101 %
b11101 )
b10011101 '
#31600
13
18
1/
1,
10
15
1;
1F
0K
b100000 "
b100000 $
b100000 Q
b11110 %
b11110 )
b10011110 '
#31800
1K
b100001 "
b100001 $
b100001 Q
b11111 %
b11111 )
b10011111 '
#32000
03
08
0/
0,
00
05
0;
0F
0K
0M
0N
0O
1P
b100010 "
b100010 $
b100010 Q
b100000 %
b100000 )
b10100000 '
#32200
1K
b100011 "
b100011 $
b100011 Q
b100001 %
b100001 )
b10100001 '
#32400
1,
1F
0K
b100100 "
b100100 $
b100100 Q
b100010 %
b100010 )
b10100010 '
#32600
1K
b100101 "
b100101 $
b100101 Q
b100011 %
b100011 )
b10100011 '
#32800
0,
0F
0K
1M
b100110 "
b100110 $
b100110 Q
b100100 %
b100100 )
b10100100 '
#33000
1K
b100111 "
b100111 $
b100111 Q
b100101 %
b100101 )
b10100101 '
#33200
1/
1,
10
1F
0K
b101000 "
b101000 $
b101000 Q
b100110 %
b100110 )
b10100110 '
#33400
1K
b101001 "
b101001 $
b101001 Q
b100111 %
b100111 )
b10100111 '
#33600
0/
0,
00
0F
0K
0M
1N
b101010 "
b101010 $
b101010 Q
b101000 %
b101000 )
b10101000 '
#33800
1K
b101011 "
b101011 $
b101011 Q
b101001 %
b101001 )
b10101001 '
#34000
1,
1F
0K
b101100 "
b101100 $
b101100 Q
b101010 %
b101010 )
b10101010 '
#34200
1K
b101101 "
b101101 $
b101101 Q
b101011 %
b101011 )
b10101011 '
#34400
0,
0F
0K
1M
b101110 "
b101110 $
b101110 Q
b101100 %
b101100 )
b10101100 '
#34600
1K
b101111 "
b101111 $
b101111 Q
b101101 %
b101101 )
b10101101 '
#34800
13
1/
1,
10
15
1F
0K
b110000 "
b110000 $
b110000 Q
b101110 %
b101110 )
b10101110 '
#35000
1K
b110001 "
b110001 $
b110001 Q
b101111 %
b101111 )
b10101111 '
#35200
03
0/
0,
00
05
0F
0K
0M
0N
1O
b110010 "
b110010 $
b110010 Q
b110000 %
b110000 )
b10110000 '
#35400
1K
b110011 "
b110011 $
b110011 Q
b110001 %
b110001 )
b10110001 '
#35600
1,
1F
0K
b110100 "
b110100 $
b110100 Q
b110010 %
b110010 )
b10110010 '
#35800
1K
b110101 "
b110101 $
b110101 Q
b110011 %
b110011 )
b10110011 '
#36000
0,
0F
0K
1M
b110110 "
b110110 $
b110110 Q
b110100 %
b110100 )
b10110100 '
#36200
1K
b110111 "
b110111 $
b110111 Q
b110101 %
b110101 )
b10110101 '
#36400
1/
1,
10
1F
0K
b111000 "
b111000 $
b111000 Q
b110110 %
b110110 )
b10110110 '
#36600
1K
b111001 "
b111001 $
b111001 Q
b110111 %
b110111 )
b10110111 '
#36800
0/
0,
00
0F
0K
0M
1N
b111010 "
b111010 $
b111010 Q
b111000 %
b111000 )
b10111000 '
#37000
1K
b111011 "
b111011 $
b111011 Q
b111001 %
b111001 )
b10111001 '
#37200
1,
1F
0K
b111100 "
b111100 $
b111100 Q
b111010 %
b111010 )
b10111010 '
#37400
1K
b111101 "
b111101 $
b111101 Q
b111011 %
b111011 )
b10111011 '
#37600
0,
0F
0K
1M
b111110 "
b111110 $
b111110 Q
b111100 %
b111100 )
b10111100 '
#37800
1K
b111111 "
b111111 $
b111111 Q
b111101 %
b111101 )
b10111101 '
#38000
1#
1>
13
18
1/
1B
1,
10
15
1;
1F
0K
b1000000 "
b0 $
b0 Q
b111110 %
b111110 )
b10111110 '
#38200
1K
b1000001 "
b1 $
b1 Q
b111111 %
b111111 )
b10111111 '
#38400
0#
0>
03
08
0/
0B
0,
00
05
0;
0F
0M
0N
0O
0P
b11 "
b11 $
b11 Q
b0 %
b0 )
b11 &
b11 (
b11000000 '
#38600
1,
1*
1-
1E
b100 "
b100 $
b100 Q
b1 %
b1 )
b11000001 '
#38800
0*
0-
0E
1F
b101 "
b101 $
b101 Q
b10 %
b10 )
b11000010 '
#39000
1*
1-
1E
b110 "
b110 $
b110 Q
b11 %
b11 )
b11000011 '
#39200
0,
0*
0-
0E
0F
1M
b111 "
b111 $
b111 Q
b100 %
b100 )
b11000100 '
#39400
1,
1/
1*
1-
11
1E
b1000 "
b1000 $
b1000 Q
b101 %
b101 )
b11000101 '
#39600
0*
0-
01
10
0E
1F
b1001 "
b1001 $
b1001 Q
b110 %
b110 )
b11000110 '
#39800
1*
1-
11
1E
b1010 "
b1010 $
b1010 Q
b111 %
b111 )
b11000111 '
#40000
0,
0/
0*
0-
00
01
0E
0F
0M
1N
b1011 "
b1011 $
b1011 Q
b1000 %
b1000 )
b11001000 '
#40200
1,
1*
1-
1E
b1100 "
b1100 $
b1100 Q
b1001 %
b1001 )
b11001001 '
#40400
0*
0-
0E
1F
b1101 "
b1101 $
b1101 Q
b1010 %
b1010 )
b11001010 '
#40600
1*
1-
1E
b1110 "
b1110 $
b1110 Q
b1011 %
b1011 )
b11001011 '
#40800
0,
0*
0-
0E
0F
1M
b1111 "
b1111 $
b1111 Q
b1100 %
b1100 )
b11001100 '
#41000
13
1,
1/
1*
1-
11
16
1E
b10000 "
b10000 $
b10000 Q
b1101 %
b1101 )
b11001101 '
#41200
0*
0-
01
06
10
15
0E
1F
b10001 "
b10001 $
b10001 Q
b1110 %
b1110 )
b11001110 '
#41400
1*
1-
11
16
1E
b10010 "
b10010 $
b10010 Q
b1111 %
b1111 )
b11001111 '
#41600
03
0,
0/
0*
0-
00
01
05
06
0E
0F
0M
0N
1O
b10011 "
b10011 $
b10011 Q
b10000 %
b10000 )
b11010000 '
#41800
1,
1*
1-
1E
b10100 "
b10100 $
b10100 Q
b10001 %
b10001 )
b11010001 '
#42000
0*
0-
0E
1F
b10101 "
b10101 $
b10101 Q
b10010 %
b10010 )
b11010010 '
#42200
1*
1-
1E
b10110 "
b10110 $
b10110 Q
b10011 %
b10011 )
b11010011 '
#42400
0,
0*
0-
0E
0F
1M
b10111 "
b10111 $
b10111 Q
b10100 %
b10100 )
b11010100 '
#42600
1,
1/
1*
1-
11
1E
b11000 "
b11000 $
b11000 Q
b10101 %
b10101 )
b11010101 '
#42800
0*
0-
01
10
0E
1F
b11001 "
b11001 $
b11001 Q
b10110 %
b10110 )
b11010110 '
#43000
1*
1-
11
1E
b11010 "
b11010 $
b11010 Q
b10111 %
b10111 )
b11010111 '
#43200
0,
0/
0*
0-
00
01
0E
0F
0M
1N
b11011 "
b11011 $
b11011 Q
b11000 %
b11000 )
b11011000 '
#43400
1,
1*
1-
1E
b11100 "
b11100 $
b11100 Q
b11001 %
b11001 )
b11011001 '
#43600
0*
0-
0E
1F
b11101 "
b11101 $
b11101 Q
b11010 %
b11010 )
b11011010 '
#43800
1*
1-
1E
b11110 "
b11110 $
b11110 Q
b11011 %
b11011 )
b11011011 '
#44000
0,
0*
0-
0E
0F
1M
b11111 "
b11111 $
b11111 Q
b11100 %
b11100 )
b11011100 '
#44200
18
13
1,
1/
1<
1*
1-
11
16
1E
b100000 "
b100000 $
b100000 Q
b11101 %
b11101 )
b11011101 '
#44400
0<
0*
0-
01
06
10
15
1;
0E
1F
b100001 "
b100001 $
b100001 Q
b11110 %
b11110 )
b11011110 '
#44600
1<
1*
1-
11
16
1E
b100010 "
b100010 $
b100010 Q
b11111 %
b11111 )
b11011111 '
#44800
03
08
0,
0/
0<
0*
0-
00
01
05
06
0;
0E
0F
0M
0N
0O
1P
b100011 "
b100011 $
b100011 Q
b100000 %
b100000 )
b11100000 '
#45000
1,
1*
1-
1E
b100100 "
b100100 $
b100100 Q
b100001 %
b100001 )
b11100001 '
#45200
0*
0-
0E
1F
b100101 "
b100101 $
b100101 Q
b100010 %
b100010 )
b11100010 '
#45400
1*
1-
1E
b100110 "
b100110 $
b100110 Q
b100011 %
b100011 )
b11100011 '
#45600
0,
0*
0-
0E
0F
1M
b100111 "
b100111 $
b100111 Q
b100100 %
b100100 )
b11100100 '
#45800
1,
1/
1*
1-
11
1E
b101000 "
b101000 $
b101000 Q
b100101 %
b100101 )
b11100101 '
#46000
0*
0-
01
10
0E
1F
b101001 "
b101001 $
b101001 Q
b100110 %
b100110 )
b11100110 '
#46200
1*
1-
11
1E
b101010 "
b101010 $
b101010 Q
b100111 %
b100111 )
b11100111 '
#46400
0,
0/
0*
0-
00
01
0E
0F
0M
1N
b101011 "
b101011 $
b101011 Q
b101000 %
b101000 )
b11101000 '
#46600
1,
1*
1-
1E
b101100 "
b101100 $
b101100 Q
b101001 %
b101001 )
b11101001 '
