cla_5bit.v
module cla5_bit(
    input [4:0] A, B,
    input c0,
    output [4:0] S,
    output c_out
    );

    wire c1, c2, c3, c4, c5;
    wire p0, p1, p2, p3, p4;
    wire g0, g1, g2, g3, g4;

    and And0(g0, A[0], B[0]);
    and And1(g1, A[1], B[1]);
    and And2(g2, A[2], B[2]);
    and And3(g3, A[3], B[3]);
    and And4(g4, A[4], B[4]);

    or Or0(p0, A[0], B[0]);
    or Or1(p1, A[1], B[1]);
    or Or2(p2, A[2], B[2]);
    or Or3(p3, A[3], B[3]);
    or Or4(p4, A[4], B[4]);

    wire c1a1;
    and c1and1(c1a1, p0, c0);
    or  c1or1(c1, c1a1, g0);
    xor s0xor1(S[0], A[0], B[0], c0);

    wire c2a2, c2a1;
    and c2and1(c2a1, p1, g0);
    and c2and2(c2a2, p1, p0, c0);
    or  c2or1(c2, c2a2, c2a1, g1);
    xor s1xor1(S[1], A[1], B[1], c1);

    wire c3a3, c3a2, c3a1;
    and c3and1(c3a1, p2, g1);
    and c3and2(c3a2, p2, p1, g0);
    and c3and3(c3a3, p2, p1, p0, c0);
    or  c3or1(c3, c3a3, c3a2, c3a1, g2);
    xor s2xor1(S[2], A[2], B[2], c2);

    wire c4a4, c4a3, c4a2, c4a1;
    and c4and1(c4a1, p3, g2);
    and c4and2(c4a2, p3, p2, g1);
    and c4and3(c4a3, p3, p2, p1, g0);
    and c4and4(c4a4, p3, p2, p1, p0, c0);
    or  c4or1(c4, c4a4, c4a3, c4a2, c4a1, g3);
    xor s3xor1(S[3], A[3], B[3], c3);

    wire c5a5, c5a4, c5a3, c5a2, c5a1;
    and c5and1(c5a1, p4, g3);
    and c5and2(c5a2, p4, p3, g2);
    and c5and3(c5a3, p4, p3, p2, g1);
    and c5and4(c5a4, p4, p3, p2, p1, g0);
    and c5and5(c5a5, p4, p3, p2, p1, p0, c0);
    or  c5or1(c5, c5a5, c5a4, c5a3, c5a2, c5a1, g4);
    xor s4xor1(S[4], A[4], B[4], c4);

    assign c_out = c5;
endmodule

cla_tb.v
`timescale 1ns / 100ps
module cla_tb;
    wire [4:0] A, B;
    wire c0;
    wire [4:0] S;
    wire c_out;

    cla5_bit adder(A, B, c0, S, c_out);
    integer i;
    assign c0 = 1'b0;
    assign {A, B} = i[7:0];
    wire [5:0] total;
    assign total = {c_out, S};

    initial begin
        for(i = 0; i < 1024; i = i+1) begin
            #20
            $display("A:%d, B:%d, => S:%d, Cout:%b, Total:%d", A, B, S, c_out, total);
            if(A+B != S) begin
                $display("Error: %d + %d != %d", A, B, S);
                $stop;
            end
        end
    end

    initial begin
        $dumpfile("cla_tb.vcd");
        $dumpvars(0, cla_tb);
    end
endmodule

OutputFiles/cla_6bit_tb.vcd
$date
	Thu Nov 07 12:59:51 2024
$end
$version
	Icarus Verilog
$end
$timescale
	100ps
$end
$scope module cla_tb $end
$var wire 1 ! c0 $end
$var wire 6 " total [5:0] $end
$var wire 1 # c_out $end
$var wire 5 $ S [4:0] $end
$var wire 5 % B [4:0] $end
$var wire 5 & A [4:0] $end
$var integer 32 ' i [31:0] $end
$scope module adder $end
$var wire 5 ( A [4:0] $end
$var wire 5 ) B [4:0] $end
$var wire 1 ! c0 $end
$var wire 1 * c1 $end
$var wire 1 + c1a1 $end
$var wire 1 , c2 $end
$var wire 1 - c2a1 $end
$var wire 1 . c2a2 $end
$var wire 1 / c3 $end
$var wire 1 0 c3a1 $end
$var wire 1 1 c3a2 $end
$var wire 1 2 c3a3 $end
$var wire 1 3 c4 $end
$var wire 1 4 c4a1 $end
$var wire 1 5 c4a2 $end
$var wire 1 6 c4a3 $end
$var wire 1 7 c4a4 $end
$var wire 1 8 c5 $end
$var wire 1 9 c5a1 $end
$var wire 1 : c5a2 $end
$var wire 1 ; c5a3 $end
$var wire 1 < c5a4 $end
$var wire 1 = c5a5 $end
$var wire 1 # c_out $end
$var wire 1 > g0 $end
$var wire 1 ? g1 $end
$var wire 1 @ g2 $end
$var wire 1 A g3 $end
$var wire 1 B g4 $end
$var wire 1 C p0 $end
$var wire 1 D p1 $end
$var wire 1 E p2 $end
$var wire 1 F p3 $end
$var wire 1 G p4 $end
$var wire 5 H S [4:0] $end
$upscope $end
$upscope $end
$enddefinitions $end
$comment Show the parameter values. $end
$dumpall
$end
#0
$dumpvars
b0 H
0G
0F
0E
0D
0C
0B
0A
0@
0?
0>
0=
0<
0;
0:
09
08
07
06
05
04
03
02
01
00
0/
0.
0-
0,
0+
0*
b0 )
b0 (
b0 '
b0 &
b0 %
b0 $
0#
b0 "
0!
$end
#200
1C
b1 "
b1 $
b1 H
b1 %
b1 )
b1 '
#400
0C
1D
b10 "
b10 $
b10 H
b10 %
b10 )
b10 '
#600
1C
b11 "
b11 $
b11 H
b11 %
b11 )
b11 '
#800
0C
0D
1E
b100 "
b100 $
b100 H
b100 %
b100 )
b100 '
#1000
1C
b101 "
b101 $
b101 H
b101 %
b101 )
b101 '
#1200
0C
1D
b110 "
b110 $
b110 H
b110 %
b110 )
b110 '
#1400
1C
b111 "
b111 $
b111 H
b111 %
b111 )
b111 '
#1600
0C
0D
0E
1F
b1000 "
b1000 $
b1000 H
b1000 %
b1000 )
b1000 '
#1800
1C
b1001 "
b1001 $
b1001 H
b1001 %
b1001 )
b1001 '
#2000
0C
1D
b1010 "
b1010 $
b1010 H
b1010 %
b1010 )
b1010 '
#2200
1C
b1011 "
b1011 $
b1011 H
b1011 %
b1011 )
b1011 '
#2400
0C
0D
1E
b1100 "
b1100 $
b1100 H
b1100 %
b1100 )
b1100 '
#2600
1C
b1101 "
b1101 $
b1101 H
b1101 %
b1101 )
b1101 '
#2800
0C
1D
b1110 "
b1110 $
b1110 H
b1110 %
b1110 )
b1110 '
#3000
1C
b1111 "
b1111 $
b1111 H
b1111 %
b1111 )
b1111 '
#3200
0C
0D
0E
0F
1G
b10000 "
b10000 $
b10000 H
b10000 %
b10000 )
b10000 '
#3400
1C
b10001 "
b10001 $
b10001 H
b10001 %
b10001 )
b10001 '
#3600
0C
1D
b10010 "
b10010 $
b10010 H
b10010 %
b10010 )
b10010 '
#3800
1C
b10011 "
b10011 $
b10011 H
b10011 %
b10011 )
b10011 '
#4000
0C
0D
1E
b10100 "
b10100 $
b10100 H
b10100 %
b10100 )
b10100 '
#4200
1C
b10101 "
b10101 $
b10101 H
b10101 %
b10101 )
b10101 '
#4400
0C
1D
b10110 "
b10110 $
b10110 H
b10110 %
b10110 )
b10110 '
#4600
1C
b10111 "
b10111 $
b10111 H
b10111 %
b10111 )
b10111 '
#4800
0C
0D
0E
1F
b11000 "
b11000 $
b11000 H
b11000 %
b11000 )
b11000 '
#5000
1C
b11001 "
b11001 $
b11001 H
b11001 %
b11001 )
b11001 '
#5200
0C
1D
b11010 "
b11010 $
b11010 H
b11010 %
b11010 )
b11010 '
#5400
1C
b11011 "
b11011 $
b11011 H
b11011 %
b11011 )
b11011 '
#5600
0C
0D
1E
b11100 "
b11100 $
b11100 H
b11100 %
b11100 )
b11100 '
#5800
1C
b11101 "
b11101 $
b11101 H
b11101 %
b11101 )
b11101 '
#6000
0C
1D
b11110 "
b11110 $
b11110 H
b11110 %
b11110 )
b11110 '
#6200
1C
b11111 "
b11111 $
b11111 H
b11111 %
b11111 )
b11111 '
#6400
0D
0E
0F
0G
b1 "
b1 $
b1 H
b0 %
b0 )
b1 &
b1 (
b100000 '
#6600
1*
1>
b10 "
b10 $
b10 H
b1 %
b1 )
b100001 '
#6800
0*
0>
1D
b11 "
b11 $
b11 H
b10 %
b10 )
b100010 '
#7000
1,
1*
1-
1>
b100 "
b100 $
b100 H
b11 %
b11 )
b100011 '
#7200
0,
0*
0-
0>
0D
1E
b101 "
b101 $
b101 H
b100 %
b100 )
b100100 '
#7400
1*
1>
b110 "
b110 $
b110 H
b101 %
b101 )
b100101 '
#7600
0*
0>
1D
b111 "
b111 $
b111 H
b110 %
b110 )
b100110 '
#7800
1,
1/
1*
1-
11
1>
b1000 "
b1000 $
b1000 H
b111 %
b111 )
b100111 '
#8000
0,
0/
0*
0-
01
0>
0D
0E
1F
b1001 "
b1001 $
b1001 H
b1000 %
b1000 )
b101000 '
#8200
1*
1>
b1010 "
b1010 $
b1010 H
b1001 %
b1001 )
b101001 '
#8400
0*
0>
1D
b1011 "
b1011 $
b1011 H
b1010 %
b1010 )
b101010 '
#8600
1,
1*
1-
1>
b1100 "
b1100 $
b1100 H
b1011 %
b1011 )
b101011 '
#8800
0,
0*
0-
0>
0D
1E
b1101 "
b1101 $
b1101 H
b1100 %
b1100 )
b101100 '
#9000
1*
1>
b1110 "
b1110 $
b1110 H
b1101 %
b1101 )
b101101 '
#9200
0*
0>
1D
b1111 "
b1111 $
b1111 H
b1110 %
b1110 )
b101110 '
#9400
13
1,
1/
1*
1-
11
16
1>
b10000 "
b10000 $
b10000 H
b1111 %
b1111 )
b101111 '
#9600
03
0,
0/
0*
0-
01
06
0>
0D
0E
0F
1G
b10001 "
b10001 $
b10001 H
b10000 %
b10000 )
b110000 '
#9800
1*
1>
b10010 "
b10010 $
b10010 H
b10001 %
b10001 )
b110001 '
#10000
0*
0>
1D
b10011 "
b10011 $
b10011 H
b10010 %
b10010 )
b110010 '
#10200
1,
1*
1-
1>
b10100 "
b10100 $
b10100 H
b10011 %
b10011 )
b110011 '
#10400
0,
0*
0-
0>
0D
1E
b10101 "
b10101 $
b10101 H
b10100 %
b10100 )
b110100 '
#10600
1*
1>
b10110 "
b10110 $
b10110 H
b10101 %
b10101 )
b110101 '
#10800
0*
0>
1D
b10111 "
b10111 $
b10111 H
b10110 %
b10110 )
b110110 '
#11000
1,
1/
1*
1-
11
1>
b11000 "
b11000 $
b11000 H
b10111 %
b10111 )
b110111 '
#11200
0,
0/
0*
0-
01
0>
0D
0E
1F
b11001 "
b11001 $
b11001 H
b11000 %
b11000 )
b111000 '
#11400
1*
1>
b11010 "
b11010 $
b11010 H
b11001 %
b11001 )
b111001 '
#11600
0*
0>
1D
b11011 "
b11011 $
b11011 H
b11010 %
b11010 )
b111010 '
#11800
1,
1*
1-
1>
b11100 "
b11100 $
b11100 H
b11011 %
b11011 )
b111011 '
#12000
0,
0*
0-
0>
0D
1E
b11101 "
b11101 $
b11101 H
b11100 %
b11100 )
b111100 '
#12200
1*
1>
b11110 "
b11110 $
b11110 H
b11101 %
b11101 )
b111101 '
#12400
0*
0>
1D
b11111 "
b11111 $
b11111 H
b11110 %
b11110 )
b111110 '
#12600
1#
18
13
1,
1/
1<
1*
1-
11
16
1>
b100000 "
b0 $
b0 H
b11111 %
b11111 )
b111111 '
#12800
0#
08
03
0,
0/
0<
0*
0-
01
06
0E
0F
0G
b10 "
b10 $
b10 H
0>
0C
b0 %
b0 )
b10 &
b10 (
b1000000 '
#13000
1C
b11 "
b11 $
b11 H
b1 %
b1 )
b1000001 '
#13200
1,
1?
0C
b100 "
b100 $
b100 H
b10 %
b10 )
b1000010 '
#13400
1C
b101 "
b101 $
b101 H
b11 %
b11 )
b1000011 '
#13600
0,
0?
0C
1E
b110 "
b110 $
b110 H
b100 %
b100 )
b1000100 '
#13800
1C
b111 "
b111 $
b111 H
b101 %
b101 )
b1000101 '
#14000
1/
1,
10
1?
0C
b1000 "
b1000 $
b1000 H
b110 %
b110 )
b1000110 '
#14200
1C
b1001 "
b1001 $
b1001 H
b111 %
b111 )
b1000111 '
#14400
0/
0,
00
0?
0C
0E
1F
b1010 "
b1010 $
b1010 H
b1000 %
b1000 )
b1001000 '
#14600
1C
b1011 "
b1011 $
b1011 H
b1001 %
b1001 )
b1001001 '
#14800
1,
1?
0C
b1100 "
b1100 $
b1100 H
b1010 %
b1010 )
b1001010 '
#15000
1C
b1101 "
b1101 $
b1101 H
b1011 %
b1011 )
b1001011 '
#15200
0,
0?
0C
1E
b1110 "
b1110 $
b1110 H
b1100 %
b1100 )
b1001100 '
#15400
1C
b1111 "
b1111 $
b1111 H
b1101 %
b1101 )
b1001101 '
#15600
13
1/
1,
10
15
1?
0C
b10000 "
b10000 $
b10000 H
b1110 %
b1110 )
b1001110 '
#15800
1C
b10001 "
b10001 $
b10001 H
b1111 %
b1111 )
b1001111 '
#16000
03
0/
0,
00
05
0?
0C
0E
0F
1G
b10010 "
b10010 $
b10010 H
b10000 %
b10000 )
b1010000 '
#16200
1C
b10011 "
b10011 $
b10011 H
b10001 %
b10001 )
b1010001 '
#16400
1,
1?
0C
b10100 "
b10100 $
b10100 H
b10010 %
b10010 )
b1010010 '
#16600
1C
b10101 "
b10101 $
b10101 H
b10011 %
b10011 )
b1010011 '
#16800
0,
0?
0C
1E
b10110 "
b10110 $
b10110 H
b10100 %
b10100 )
b1010100 '
#17000
1C
b10111 "
b10111 $
b10111 H
b10101 %
b10101 )
b1010101 '
#17200
1/
1,
10
1?
0C
b11000 "
b11000 $
b11000 H
b10110 %
b10110 )
b1010110 '
#17400
1C
b11001 "
b11001 $
b11001 H
b10111 %
b10111 )
b1010111 '
#17600
0/
0,
00
0?
0C
0E
1F
b11010 "
b11010 $
b11010 H
b11000 %
b11000 )
b1011000 '
#17800
1C
b11011 "
b11011 $
b11011 H
b11001 %
b11001 )
b1011001 '
#18000
1,
1?
0C
b11100 "
b11100 $
b11100 H
b11010 %
b11010 )
b1011010 '
#18200
1C
b11101 "
b11101 $
b11101 H
b11011 %
b11011 )
b1011011 '
#18400
0,
0?
0C
1E
b11110 "
b11110 $
b11110 H
b11100 %
b11100 )
b1011100 '
#18600
1C
b11111 "
b11111 $
b11111 H
b11101 %
b11101 )
b1011101 '
#18800
13
1#
18
1/
1,
10
15
1;
1?
0C
b100000 "
b0 $
b0 H
b11110 %
b11110 )
b1011110 '
#19000
1C
b100001 "
b1 $
b1 H
b11111 %
b11111 )
b1011111 '
#19200
03
0#
08
0/
0,
00
05
0;
0?
0E
0F
0G
b11 "
b11 $
b11 H
b0 %
b0 )
b11 &
b11 (
b1100000 '
#19400
1,
1*
1-
1>
b100 "
b100 $
b100 H
b1 %
b1 )
b1100001 '
#19600
0*
0-
0>
1?
b101 "
b101 $
b101 H
b10 %
b10 )
b1100010 '
#19800
1*
1-
1>
b110 "
b110 $
b110 H
b11 %
b11 )
b1100011 '
#20000
0,
0*
0-
0>
0?
1E
b111 "
b111 $
b111 H
b100 %
b100 )
b1100100 '
#20200
1,
1/
1*
1-
11
1>
b1000 "
b1000 $
b1000 H
b101 %
b101 )
b1100101 '
#20400
0*
0-
01
10
0>
1?
b1001 "
b1001 $
b1001 H
b110 %
b110 )
b1100110 '
#20600
1*
1-
11
1>
b1010 "
b1010 $
b1010 H
b111 %
b111 )
b1100111 '
#20800
0,
0/
0*
0-
00
01
0>
0?
0E
1F
b1011 "
b1011 $
b1011 H
b1000 %
b1000 )
b1101000 '
#21000
1,
1*
1-
1>
b1100 "
b1100 $
b1100 H
b1001 %
b1001 )
b1101001 '
#21200
0*
0-
0>
1?
b1101 "
b1101 $
b1101 H
b1010 %
b1010 )
b1101010 '
#21400
1*
1-
1>
b1110 "
b1110 $
b1110 H
b1011 %
b1011 )
b1101011 '
#21600
0,
0*
0-
0>
0?
1E
b1111 "
b1111 $
b1111 H
b1100 %
b1100 )
b1101100 '
#21800
13
1,
1/
1*
1-
11
16
1>
b10000 "
b10000 $
b10000 H
b1101 %
b1101 )
b1101101 '
#22000
0*
0-
01
06
10
15
0>
1?
b10001 "
b10001 $
b10001 H
b1110 %
b1110 )
b1101110 '
#22200
1*
1-
11
16
1>
b10010 "
b10010 $
b10010 H
b1111 %
b1111 )
b1101111 '
#22400
03
0,
0/
0*
0-
00
01
05
06
0>
0?
0E
0F
1G
b10011 "
b10011 $
b10011 H
b10000 %
b10000 )
b1110000 '
#22600
1,
1*
1-
1>
b10100 "
b10100 $
b10100 H
b10001 %
b10001 )
b1110001 '
#22800
0*
0-
0>
1?
b10101 "
b10101 $
b10101 H
b10010 %
b10010 )
b1110010 '
#23000
1*
1-
1>
b10110 "
b10110 $
b10110 H
b10011 %
b10011 )
b1110011 '
#23200
0,
0*
0-
0>
0?
1E
b10111 "
b10111 $
b10111 H
b10100 %
b10100 )
b1110100 '
#23400
1,
1/
1*
1-
11
1>
b11000 "
b11000 $
b11000 H
b10101 %
b10101 )
b1110101 '
#23600
0*
0-
01
10
0>
1?
b11001 "
b11001 $
b11001 H
b10110 %
b10110 )
b1110110 '
#23800
1*
1-
11
1>
b11010 "
b11010 $
b11010 H
b10111 %
b10111 )
b1110111 '
#24000
0,
0/
0*
0-
00
01
0>
0?
0E
1F
b11011 "
b11011 $
b11011 H
b11000 %
b11000 )
b1111000 '
#24200
1,
1*
1-
1>
b11100 "
b11100 $
b11100 H
b11001 %
b11001 )
b1111001 '
#24400
0*
0-
0>
1?
b11101 "
b11101 $
b11101 H
b11010 %
b11010 )
b1111010 '
#24600
1*
1-
1>
b11110 "
b11110 $
b11110 H
b11011 %
b11011 )
b1111011 '
#24800
0,
0*
0-
0>
0?
1E
b11111 "
b11111 $
b11111 H
b11100 %
b11100 )
b1111100 '
#25000
1#
18
13
1,
1/
1<
1*
1-
11
16
1>
b100000 "
b0 $
b0 H
b11101 %
b11101 )
b1111101 '
#25200
0<
0*
0-
01
06
10
15
1;
0>
1?
b100001 "
b1 $
b1 H
b11110 %
b11110 )
b1111110 '
#25400
1<
1*
1-
11
16
1>
b100010 "
b10 $
b10 H
b11111 %
b11111 )
b1111111 '
#25600
0#
08
03
0/
0<
0*
0,
00
05
0;
0-
01
06
0F
0G
b100 "
b100 $
b100 H
0>
0?
0C
0D
b0 %
b0 )
b100 &
b100 (
b10000000 '
#25800
1C
b101 "
b101 $
b101 H
b1 %
b1 )
b10000001 '
#26000
0C
1D
b110 "
b110 $
b110 H
b10 %
b10 )
b10000010 '
#26200
1C
b111 "
b111 $
b111 H
b11 %
b11 )
b10000011 '
#26400
1/
1@
0C
0D
b1000 "
b1000 $
b1000 H
b100 %
b100 )
b10000100 '
#26600
1C
b1001 "
b1001 $
b1001 H
b101 %
b101 )
b10000101 '
#26800
0C
1D
b1010 "
b1010 $
b1010 H
b110 %
b110 )
b10000110 '
#27000
1C
b1011 "
b1011 $
b1011 H
b111 %
b111 )
b10000111 '
#27200
0/
0@
0C
0D
1F
b1100 "
b1100 $
b1100 H
b1000 %
b1000 )
b10001000 '
#27400
1C
b1101 "
b1101 $
b1101 H
b1001 %
b1001 )
b10001001 '
#27600
0C
1D
b1110 "
b1110 $
b1110 H
b1010 %
b1010 )
b10001010 '
#27800
1C
b1111 "
b1111 $
b1111 H
b1011 %
b1011 )
b10001011 '
#28000
13
1/
14
1@
0C
0D
b10000 "
b10000 $
b10000 H
b1100 %
b1100 )
b10001100 '
#28200
1C
b10001 "
b10001 $
b10001 H
b1101 %
b1101 )
b10001101 '
#28400
0C
1D
b10010 "
b10010 $
b10010 H
b1110 %
b1110 )
b10001110 '
#28600
1C
b10011 "
b10011 $
b10011 H
b1111 %
b1111 )
b10001111 '
#28800
03
0/
04
0@
0C
0D
0F
1G
b10100 "
b10100 $
b10100 H
b10000 %
b10000 )
b10010000 '
#29000
1C
b10101 "
b10101 $
b10101 H
b10001 %
b10001 )
b10010001 '
#29200
0C
1D
b10110 "
b10110 $
b10110 H
b10010 %
b10010 )
b10010010 '
#29400
1C
b10111 "
b10111 $
b10111 H
b10011 %
b10011 )
b10010011 '
#29600
1/
1@
0C
0D
b11000 "
b11000 $
b11000 H
b10100 %
b10100 )
b10010100 '
#29800
1C
b11001 "
b11001 $
b11001 H
b10101 %
b10101 )
b10010101 '
#30000
0C
1D
b11010 "
b11010 $
b11010 H
b10110 %
b10110 )
b10010110 '
#30200
1C
b11011 "
b11011 $
b11011 H
b10111 %
b10111 )
b10010111 '
#30400
0/
0@
0C
0D
1F
b11100 "
b11100 $
b11100 H
b11000 %
b11000 )
b10011000 '
#30600
1C
b11101 "
b11101 $
b11101 H
b11001 %
b11001 )
b10011001 '
#30800
0C
1D
b11110 "
b11110 $
b11110 H
b11010 %
b11010 )
b10011010 '
#31000
1C
b11111 "
b11111 $
b11111 H
b11011 %
b11011 )
b10011011 '
#31200
13
1#
18
1/
14
1:
1@
0C
0D
b100000 "
b0 $
b0 H
b11100 %
b11100 )
b10011100 '
#31400
1C
b100001 "
b1 $
b1 H
b11101 %
b11101 )
b10011101 '
#31600
0C
1D
b100010 "
b10 $
b10 H
b11110 %
b11110 )
b10011110 '
#31800
1C
b100011 "
b11 $
b11 H
b11111 %
b11111 )
b10011111 '
#32000
03
0#
08
0/
04
0:
0@
0D
0F
0G
b101 "
b101 $
b101 H
b0 %
b0 )
b101 &
b101 (
b10100000 '
#32200
1*
1>
b110 "
b110 $
b110 H
b1 %
b1 )
b10100001 '
#32400
0*
0>
1D
b111 "
b111 $
b111 H
b10 %
b10 )
b10100010 '
#32600
1,
1/
1*
1-
11
1>
b1000 "
b1000 $
b1000 H
b11 %
b11 )
b10100011 '
#32800
0,
0*
0-
01
0>
1@
0D
b1001 "
b1001 $
b1001 H
b100 %
b100 )
b10100100 '
#33000
1*
1>
b1010 "
b1010 $
b1010 H
b101 %
b101 )
b10100101 '
#33200
0*
0>
1D
b1011 "
b1011 $
b1011 H
b110 %
b110 )
b10100110 '
#33400
1,
1*
1-
11
1>
b1100 "
b1100 $
b1100 H
b111 %
b111 )
b10100111 '
#33600
0,
0*
0/
0-
01
0>
0@
0D
1F
b1101 "
b1101 $
b1101 H
b1000 %
b1000 )
b10101000 '
#33800
1*
1>
b1110 "
b1110 $
b1110 H
b1001 %
b1001 )
b10101001 '
#34000
0*
0>
1D
b1111 "
b1111 $
b1111 H
b1010 %
b1010 )
b10101010 '
#34200
13
1,
1/
1*
1-
11
16
1>
b10000 "
b10000 $
b10000 H
b1011 %
b1011 )
b10101011 '
#34400
0,
0*
14
0-
01
06
0>
1@
0D
b10001 "
b10001 $
b10001 H
b1100 %
b1100 )
b10101100 '
#34600
1*
1>
b10010 "
b10010 $
b10010 H
b1101 %
b1101 )
b10101101 '
#34800
0*
0>
1D
b10011 "
b10011 $
b10011 H
b1110 %
b1110 )
b10101110 '
#35000
1,
1*
1-
11
16
1>
b10100 "
b10100 $
b10100 H
b1111 %
b1111 )
b10101111 '
#35200
03
0,
0*
0/
0-
01
04
06
0>
0@
0D
0F
1G
b10101 "
b10101 $
b10101 H
b10000 %
b10000 )
b10110000 '
#35400
1*
1>
b10110 "
b10110 $
b10110 H
b10001 %
b10001 )
b10110001 '
#35600
0*
0>
1D
b10111 "
b10111 $
b10111 H
b10010 %
b10010 )
b10110010 '
#35800
1,
1/
1*
1-
11
1>
b11000 "
b11000 $
b11000 H
b10011 %
b10011 )
b10110011 '
#36000
0,
0*
0-
01
0>
1@
0D
b11001 "
b11001 $
b11001 H
b10100 %
b10100 )
b10110100 '
#36200
1*
1>
b11010 "
b11010 $
b11010 H
b10101 %
b10101 )
b10110101 '
#36400
0*
0>
1D
b11011 "
b11011 $
b11011 H
b10110 %
b10110 )
b10110110 '
#36600
1,
1*
1-
11
1>
b11100 "
b11100 $
b11100 H
b10111 %
b10111 )
b10110111 '
#36800
0,
0*
0/
0-
01
0>
0@
0D
1F
b11101 "
b11101 $
b11101 H
b11000 %
b11000 )
b10111000 '
#37000
1*
1>
b11110 "
b11110 $
b11110 H
b11001 %
b11001 )
b10111001 '
#37200
0*
0>
1D
b11111 "
b11111 $
b11111 H
b11010 %
b11010 )
b10111010 '
#37400
1#
18
13
1,
1/
1<
1*
1-
11
16
1>
b100000 "
b0 $
b0 H
b11011 %
b11011 )
b10111011 '
#37600
0,
0<
0*
14
1:
0-
01
06
0>
1@
0D
b100001 "
b1 $
b1 H
b11100 %
b11100 )
b10111100 '
#37800
1*
1>
b100010 "
b10 $
b10 H
b11101 %
b11101 )
b10111101 '
#38000
0*
0>
1D
b100011 "
b11 $
b11 H
b11110 %
b11110 )
b10111110 '
#38200
1,
1<
1*
1-
11
16
1>
b100100 "
b100 $
b100 H
b11111 %
b11111 )
b10111111 '
#38400
0#
08
03
0,
0<
0/
04
0:
0*
0-
01
06
0@
0F
0G
b110 "
b110 $
b110 H
0>
0C
b0 %
b0 )
b110 &
b110 (
b11000000 '
#38600
1C
b111 "
b111 $
b111 H
b1 %
b1 )
b11000001 '
#38800
1/
1,
10
1?
0C
b1000 "
b1000 $
b1000 H
b10 %
b10 )
b11000010 '
#39000
1C
b1001 "
b1001 $
b1001 H
b11 %
b11 )
b11000011 '
#39200
0,
00
0?
1@
0C
b1010 "
b1010 $
b1010 H
b100 %
b100 )
b11000100 '
#39400
1C
b1011 "
b1011 $
b1011 H
b101 %
b101 )
b11000101 '
#39600
1,
10
1?
0C
b1100 "
b1100 $
b1100 H
b110 %
b110 )
b11000110 '
#39800
1C
b1101 "
b1101 $
b1101 H
b111 %
b111 )
b11000111 '
#40000
0/
0,
00
0?
0@
0C
1F
b1110 "
b1110 $
b1110 H
b1000 %
b1000 )
b11001000 '
#40200
1C
b1111 "
b1111 $
b1111 H
b1001 %
b1001 )
b11001001 '
#40400
13
1/
1,
10
15
1?
0C
b10000 "
b10000 $
b10000 H
b1010 %
b1010 )
b11001010 '
#40600
1C
b10001 "
b10001 $
b10001 H
b1011 %
b1011 )
b11001011 '
#40800
0,
00
05
14
0?
1@
0C
b10010 "
b10010 $
b10010 H
b1100 %
b1100 )
b11001100 '
#41000
1C
b10011 "
b10011 $
b10011 H
b1101 %
b1101 )
b11001101 '
#41200
1,
10
15
1?
0C
b10100 "
b10100 $
b10100 H
b1110 %
b1110 )
b11001110 '
#41400
1C
b10101 "
b10101 $
b10101 H
b1111 %
b1111 )
b11001111 '
#41600
03
0/
0,
00
04
05
0?
0@
0C
0F
1G
b10110 "
b10110 $
b10110 H
b10000 %
b10000 )
b11010000 '
#41800
1C
b10111 "
b10111 $
b10111 H
b10001 %
b10001 )
b11010001 '
#42000
1/
1,
10
1?
0C
b11000 "
b11000 $
b11000 H
b10010 %
b10010 )
b11010010 '
#42200
1C
b11001 "
b11001 $
b11001 H
b10011 %
b10011 )
b11010011 '
#42400
0,
00
0?
1@
0C
b11010 "
b11010 $
b11010 H
b10100 %
b10100 )
b11010100 '
#42600
1C
b11011 "
b11011 $
b11011 H
b10101 %
b10101 )
b11010101 '
#42800
1,
10
1?
0C
b11100 "
b11100 $
b11100 H
b10110 %
b10110 )
b11010110 '
#43000
1C
b11101 "
b11101 $
b11101 H
b10111 %
b10111 )
b11010111 '
#43200
0/
0,
00
0?
0@
0C
1F
b11110 "
b11110 $
b11110 H
b11000 %
b11000 )
b11011000 '
#43400
1C
b11111 "
b11111 $
b11111 H
b11001 %
b11001 )
b11011001 '
#43600
13
1#
18
1/
1,
10
15
1;
1?
0C
b100000 "
b0 $
b0 H
b11010 %
b11010 )
b11011010 '
#43800
1C
b100001 "
b1 $
b1 H
b11011 %
b11011 )
b11011011 '
#44000
0,
00
05
0;
14
1:
0?
1@
0C
b100010 "
b10 $
b10 H
b11100 %
b11100 )
b11011100 '
#44200
1C
b100011 "
b11 $
b11 H
b11101 %
b11101 )
b11011101 '
#44400
1,
10
15
1;
1?
0C
b100100 "
b100 $
b100 H
b11110 %
b11110 )
b11011110 '
#44600
1C
b100101 "
b101 $
b101 H
b11111 %
b11111 )
b11011111 '
#44800
03
0#
08
0/
0,
00
04
05
0:
0;
0?
0@
0F
0G
b111 "
b111 $
b111 H
b0 %
b0 )
b111 &
b111 (
b11100000 '
#45000
1,
1/
1*
1-
11
1>
b1000 "
b1000 $
b1000 H
b1 %
b1 )
b11100001 '
#45200
0*
0-
01
10
0>
1?
b1001 "
b1001 $
b1001 H
b10 %
b10 )
b11100010 '
#45400
1*
1-
11
1>
b1010 "
b1010 $
b1010 H
b11 %
b11 )
b11100011 '
#45600
0,
0*
0-
01
00
0>
0?
1@
b1011 "
b1011 $
b1011 H
b100 %
b100 )
b11100100 '
#45800
1,
1*
1-
11
1>
b1100 "
b1100 $
b1100 H
b101 %
b101 )
b11100101 '
#46000
0*
0-
01
10
0>
1?
b1101 "
b1101 $
b1101 H
b110 %
b110 )
b11100110 '
#46200
1*
1-
11
1>
b1110 "
b1110 $
b1110 H
b111 %
b111 )
b11100111 '
#46400
0,
0/
0*
0-
01
00
0>
0?
0@
1F
b1111 "
b1111 $
b1111 H
b1000 %
b1000 )
b11101000 '
#46600
13
1,
1/
1*
1-
11
16
1>
b10000 "
b10000 $
b10000 H
b1001 %
b1001 )
b11101001 '
#46800
0*
0-
01
06
10
15
0>
1?
b10001 "
b10001 $
b10001 H
b1010 %
b1010 )
b11101010 '
#47000
1*
1-
11
16
1>
b10010 "
b10010 $
b10010 H
b1011 %
b1011 )
b11101011 '
#47200
0,
0*
0-
01
06
00
05
14
0>
0?
1@
b10011 "
b10011 $
b10011 H
b1100 %
b1100 )
b11101100 '
#47400
1,
1*
1-
11
16
1>
b10100 "
b10100 $
b10100 H
b1101 %
b1101 )
b11101101 '
#47600
0*
0-
01
06
10
15
0>
1?
b10101 "
b10101 $
b10101 H
b1110 %
b1110 )
b11101110 '
#47800
1*
1-
11
16
1>
b10110 "
b10110 $
b10110 H
b1111 %
b1111 )
b11101111 '
#48000
03
0,
0/
0*
0-
01
00
04
05
06
0>
0?
0@
0F
1G
b10111 "
b10111 $
b10111 H
b10000 %
b10000 )
b11110000 '
#48200
1,
1/
1*
1-
11
1>
b11000 "
b11000 $
b11000 H
b10001 %
b10001 )
b11110001 '
#48400
0*
0-
01
10
0>
1?
b11001 "
b11001 $
b11001 H
b10010 %
b10010 )
b11110010 '
#48600
1*
1-
11
1>
b11010 "
b11010 $
b11010 H
b10011 %
b10011 )
b11110011 '
#48800
0,
0*
0-
01
00
0>
0?
1@
b11011 "
b11011 $
b11011 H
b10100 %
b10100 )
b11110100 '
